{ "columns":20,
 "image":"chompermazetiles.png",
 "imageheight":96,
 "imagewidth":320,
 "margin":0,
 "name":"chompermazetiles",
 "spacing":0,
 "tilecount":120,
 "tiledversion":"1.9.1",
 "tileheight":16,
 "tiles":[
        {
         "id":0,
         "objectgroup":
            {
             "draworder":"index",
             "id":2,
             "name":"",
             "objects":[
                    {
                     "class":"",
                     "height":5.9375,
                     "id":1,
                     "name":"",
                     "rotation":0,
                     "visible":true,
                     "width":8.1875,
                     "x":3.9375,
                     "y":10.0625
                    }, 
                    {
                     "class":"",
                     "height":7.8125,
                     "id":2,
                     "name":"",
                     "rotation":0,
                     "visible":true,
                     "width":3.75,
                     "x":12.1875,
                     "y":4.0625
                    }, 
                    {
                     "class":"",
                     "ellipse":true,
                     "height":6.875,
                     "id":3,
                     "name":"",
                     "rotation":0,
                     "visible":true,
                     "width":6.9375,
                     "x":4.75,
                     "y":4.125
                    }],
             "opacity":1,
             "type":"objectgroup",
             "visible":true,
             "x":0,
             "y":0
            }
        }, 
        {
         "id":1,
         "objectgroup":
            {
             "draworder":"index",
             "id":2,
             "name":"",
             "objects":[
                    {
                     "class":"",
                     "height":7.875,
                     "id":1,
                     "name":"",
                     "rotation":0,
                     "visible":true,
                     "width":16.0625,
                     "x":0.0625,
                     "y":3.9375
                    }],
             "opacity":1,
             "type":"objectgroup",
             "visible":true,
             "x":0,
             "y":0
            }
        }, 
        {
         "id":5,
         "objectgroup":
            {
             "draworder":"index",
             "id":2,
             "name":"",
             "objects":[
                    {
                     "class":"",
                     "height":8,
                     "id":1,
                     "name":"",
                     "rotation":0,
                     "visible":true,
                     "width":11.875,
                     "x":0,
                     "y":3.9375
                    }, 
                    {
                     "class":"",
                     "height":12,
                     "id":2,
                     "name":"",
                     "rotation":0,
                     "visible":true,
                     "width":7.75,
                     "x":4,
                     "y":3.9375
                    }],
             "opacity":1,
             "type":"objectgroup",
             "visible":true,
             "x":0,
             "y":0
            }
        }, 
        {
         "id":20,
         "objectgroup":
            {
             "draworder":"index",
             "id":2,
             "name":"",
             "objects":[
                    {
                     "class":"",
                     "height":15.9375,
                     "id":1,
                     "name":"",
                     "rotation":0,
                     "visible":true,
                     "width":8.125,
                     "x":4,
                     "y":0.0625
                    }],
             "opacity":1,
             "type":"objectgroup",
             "visible":true,
             "x":0,
             "y":0
            }
        }, 
        {
         "id":25,
         "objectgroup":
            {
             "draworder":"index",
             "id":2,
             "name":"",
             "objects":[
                    {
                     "class":"",
                     "height":15.9375,
                     "id":1,
                     "name":"",
                     "rotation":0,
                     "visible":true,
                     "width":8.0625,
                     "x":3.875,
                     "y":0
                    }],
             "opacity":1,
             "type":"objectgroup",
             "visible":true,
             "x":0,
             "y":0
            }
        }, 
        {
         "id":85,
         "objectgroup":
            {
             "draworder":"index",
             "id":2,
             "name":"",
             "objects":[
                    {
                     "class":"",
                     "height":15.875,
                     "id":1,
                     "name":"",
                     "rotation":0,
                     "visible":true,
                     "width":8,
                     "x":4,
                     "y":0.0625
                    }],
             "opacity":1,
             "type":"objectgroup",
             "visible":true,
             "x":0,
             "y":0
            }
        }, 
        {
         "id":100,
         "objectgroup":
            {
             "draworder":"index",
             "id":3,
             "name":"",
             "objects":[
                    {
                     "class":"",
                     "height":12,
                     "id":2,
                     "name":"",
                     "rotation":0,
                     "visible":true,
                     "width":8.0625,
                     "x":4,
                     "y":0
                    }, 
                    {
                     "class":"",
                     "height":7.9375,
                     "id":3,
                     "name":"",
                     "rotation":0,
                     "visible":true,
                     "width":12,
                     "x":4,
                     "y":4.0625
                    }],
             "opacity":1,
             "type":"objectgroup",
             "visible":true,
             "x":0,
             "y":0
            }
        }, 
        {
         "id":104,
         "objectgroup":
            {
             "draworder":"index",
             "id":2,
             "name":"",
             "objects":[
                    {
                     "class":"",
                     "height":8.125,
                     "id":1,
                     "name":"",
                     "rotation":0,
                     "visible":true,
                     "width":16,
                     "x":0,
                     "y":3.9375
                    }],
             "opacity":1,
             "type":"objectgroup",
             "visible":true,
             "x":0,
             "y":0
            }
        }, 
        {
         "id":105,
         "objectgroup":
            {
             "draworder":"index",
             "id":2,
             "name":"",
             "objects":[
                    {
                     "class":"",
                     "height":11.8125,
                     "id":1,
                     "name":"",
                     "rotation":0,
                     "visible":true,
                     "width":7.875,
                     "x":4.0625,
                     "y":0.0625
                    }, 
                    {
                     "class":"",
                     "height":7.9375,
                     "id":2,
                     "name":"",
                     "rotation":0,
                     "visible":true,
                     "width":12,
                     "x":-0.0625,
                     "y":4
                    }],
             "opacity":1,
             "type":"objectgroup",
             "visible":true,
             "x":0,
             "y":0
            }
        }],
 "tilewidth":16,
 "type":"tileset",
 "version":"1.8"
}